missingpy/__init__.py
missingpy/knnimpute.py
missingpy/missforest.py
missingpy/pairwise_ext.py
missingpy/pairwise_external.py
missingpy/utils.py
missingpy/utils_external.py
missingpy/tests/__init__.py
missingpy/tests/test_knnimpute.py
missingpy/tests/test_missforest.py
missingpy-0.2.0.dist-info/LICENSE
missingpy-0.2.0.dist-info/METADATA
missingpy-0.2.0.dist-info/WHEEL
missingpy-0.2.0.dist-info/top_level.txt
missingpy-0.2.0.dist-info/RECORD
