Metadata-Version: 2.1
Name: missingpy
Version: 0.2.0
Summary: Missing Data Imputation for Python
Home-page: https://github.com/epsilon-machine/missingpy
Author: Ashim Bhattarai
License: UNKNOWN
Platform: UNKNOWN
Classifier: Programming Language :: Python :: 3
Classifier: License :: OSI Approved :: GNU General Public License v3 (GPLv3)
Classifier: Operating System :: OS Independent
